zeppelin/__init__.py
zeppelin/data_models/__init__.py
zeppelin/data_models/base_data_model.py
zeppelin/data_models/field.py
zeppelin/data_sources/__init__.py
zeppelin/data_sources/data_sources.py
zeppelin-0.1.0.dist-info/LICENSE
zeppelin-0.1.0.dist-info/WHEEL
zeppelin-0.1.0.dist-info/METADATA
zeppelin-0.1.0.dist-info/RECORD
